{
  "schemaVersion": "2026-06-21.panda-bridge.desktop-release.v1",
  "releaseId": "panda-bridge-desktop-v0.1.0",
  "product": "panda-bridge-desktop",
  "appName": "Panda Bridge",
  "bundleIdentifier": "cc.otherline.panda-bridge",
  "protocol": "panda-bridge",
  "version": "0.1.0",
  "channel": "stable",
  "assetBaseUrls": {
    "production": "https://assets.bridge.chaos-realms.cc",
    "test": "https://assets-bridge-test.chaos-realms.cc"
  },
  "manifest": {
    "latestPath": "/downloads/panda-bridge-desktop/latest.json",
    "versionedPath": "/downloads/releases/v0.1.0/panda-bridge-desktop-v0.1.0.json"
  },
  "targets": {
    "macos": {
      "platform": "macos",
      "package": "dmg",
      "distDir": "dist/desktop/macos",
      "fileName": "panda-bridge-macos.dmg",
      "versionedFileName": "panda-bridge-desktop-v0.1.0-macos.dmg",
      "downloadPath": "/downloads/panda-bridge-macos.dmg",
      "versionedDownloadPath": "/downloads/releases/v0.1.0/panda-bridge-desktop-v0.1.0-macos.dmg",
      "contentType": "application/x-apple-diskimage",
      "minimumBytes": 1048576,
      "sha256": "7d908a82f4fa854c9b655b634b019c6d5897f8f6409d4eeffba27c990a014274"
    },
    "windows-x64": {
      "platform": "windows",
      "arch": "x64",
      "package": "portable-zip",
      "distDir": "dist/desktop/windows",
      "fileName": "panda-bridge-windows-x64.zip",
      "versionedFileName": "panda-bridge-desktop-v0.1.0-windows-x64.zip",
      "downloadPath": "/downloads/panda-bridge-windows-x64.zip",
      "versionedDownloadPath": "/downloads/releases/v0.1.0/panda-bridge-desktop-v0.1.0-windows-x64.zip",
      "contentType": "application/zip",
      "minimumBytes": 1048576,
      "sha256": "92aa1ab30ffe6e3a3e15259306731de3880adbff088b06500b9406b1f698834a"
    }
  },
  "releaseGate": {
    "prepareCommand": "npm run release:desktop:prepare",
    "verifyCommand": "npm run release:desktop:verify",
    "publicAuditCommand": "npm run release:desktop:audit-public",
    "productionUploadRequires": [
      "release packet with affected assets and rollback/roll-forward plan",
      "macOS DMG and Windows x64 zip produced by release:desktop:prepare",
      "macOS package summary reports Developer ID signing, hardened runtime, notarization, and stapling",
      "release:desktop:verify passes against local artifacts and sha256",
      "public upload target confirmed without printing credentials",
      "release:desktop:audit-public passes after upload before announcing links"
    ]
  }
}
